django_notifications/__about__.py
django_notifications/__init__.py
django_notifications/apps.py
django_notifications/signals.py
django_notifications/admin/__init__.py
django_notifications/admin/filters.py
django_notifications/admin/forms.py
django_notifications/admin/inlines.py
django_notifications/locale/fr/LC_MESSAGES/django.mo
django_notifications/locale/fr/LC_MESSAGES/django.po
django_notifications/management/__init__.py
django_notifications/management/commands/__init__.py
django_notifications/management/commands/clean_notifications.py
django_notifications/management/commands/send_notifications.py
django_notifications/migrations/0001_initial.py
django_notifications/migrations/0002_notificationconfig.py
django_notifications/migrations/0003_auto_20220207_1157.py
django_notifications/migrations/0004_notification_from_email.py
django_notifications/migrations/0005_debugging.py
django_notifications/migrations/0006_notification_as_bcc_and_more.py
django_notifications/migrations/0007_alter_attachment_attachment_file_and_more.py
django_notifications/migrations/__init__.py
django_notifications/models/__init__.py
django_notifications/models/config.py
django_notifications/models/helpers.py
django_notifications/templates/django_notifications/base_email.html
django_notifications/templates/django_notifications/base_email.txt.tpl
django_notifications/templates/django_notifications/admin/snippets/dates.html
django_notifications/templates/django_notifications/admin/snippets/recipients.html
django_notifications/templates/django_notifications/admin/snippets/related_object.html
django_notifications/templates/django_notifications/admin/snippets/states.html
django_notifications/templates/django_notifications/admin/snippets/subject.html
django_notifications/templates/django_notifications/debug/body.txt.tpl
django_notifications/templatetags/__init__.py
django_notifications/templatetags/notifications_tags.py
django_notifications/tests/__init__.py
django_delayed_notifications-0.12.3.dist-info/METADATA
django_delayed_notifications-0.12.3.dist-info/WHEEL
django_delayed_notifications-0.12.3.dist-info/licenses/LICENSE
django_delayed_notifications-0.12.3.dist-info/RECORD
