Metadata-Version: 2.4
Name: django-delayed-notifications
Version: 0.12.3
Summary: django-delayed-notifications provides tracking of notifications, and delayed sending.
Project-URL: Homepage, https://gitlab.com/frague59/django-delayed-notifications
Project-URL: Source, https://gitlab.com/frague59/django-delayed-notifications
Author-email: François GUÉRIN <frague59@gmail.com>
Maintainer-email: François GUÉRIN <frague59@gmail.com>
License: MIT
License-File: LICENSE
Keywords: delayed sending,django,notifications
Classifier: Development Status :: 4 - Beta
Classifier: Environment :: Web Environment
Classifier: Framework :: Django
Classifier: Framework :: Django :: 3.2
Classifier: Framework :: Django :: 4.2
Classifier: Framework :: Django :: 5.2
Classifier: Intended Audience :: Developers
Classifier: License :: OSI Approved :: MIT License
Classifier: Natural Language :: English
Classifier: Natural Language :: French
Classifier: Operating System :: OS Independent
Classifier: Programming Language :: Python
Classifier: Programming Language :: Python :: 3
Classifier: Programming Language :: Python :: 3.9
Classifier: Programming Language :: Python :: 3.10
Classifier: Programming Language :: Python :: 3.11
Classifier: Topic :: Communications :: Email
Classifier: Topic :: Internet
Classifier: Topic :: Internet :: WWW/HTTP :: WSGI :: Application
Classifier: Topic :: Software Development :: Libraries :: Python Modules
Requires-Python: >=3.11
Requires-Dist: beautifulsoup4~=4.11
Requires-Dist: django-ckeditor-5
Requires-Dist: django-currentuser<1.0,>=0.6.0
Requires-Dist: django-solo<3.0,>=2.0
Requires-Dist: django<6.0,>=3.2
Provides-Extra: docs
Requires-Dist: sphinx-rtd-theme; extra == 'docs'
Requires-Dist: sphinx>=1.5.5; extra == 'docs'
